{
  "description": "The Code Moon NFT collection is inspired by the exciting vision for the future of humanity. In this collection, you will discover thrilling illustrations depicting scenes from life on the Moon, where people have retreated following the ecological challenges of Earth. Each image reveals fascinating details of life and technological progress on the Moon, presented through exquisite artwork and innovative design. Become a part of this unique collection and preserve the moment from the beginning of a new era for humanity. Every NFT from this collection can be bought and sold on OKX NFT, ensuring seamless access to a global marketplace for collectors and traders alike.",
  "discord_link": "",
  "iconinscription_icon": "98224762e6bdc12fdc10dcbf73d250e3c6f6cd995d93268f7cf8fb761b399076i0",
  "name": "Code Moon",
  "slug": "Code_Moon",
  "twitter_link": "https://x.com/BochukovRumen",
  "website_link": "https://www.okx.com/web3/marketplace/nft/collection/fractal/lunar-base-1"
}
