{
  "description": "bitRex 🦖 – A wild pack of comical, voxel T-Rex avatars stomping onto the blockchain! Inscribed on Fractal Bitcoin, each bitRex comes packed with unique traits and toggleable actions. Grab a Mother on Fractal, and we’ll airdrop you a Father duplicate on Bitcoin Mainnet. The future? Full of surprises. 🚀🔥",
  "discord_link": "https://discord.gg/CPeDcmPT5V",
  "icon": "1220cc7f85a0364ebb5304ea7e7ad8ce08deee6a5794274a00776664dd09551bi0",
  "name": "bitrex🦖",
  "slug": "bitrex",
  "twitter_link": "https://x.com/CryptoTrexNFT",
  "website_link": "https://thelonelybit.org/BitRex_Run/"
}
